[
{
    "path" : "./logs/v2/20210913/36/full.json",
    "module_name" : "main::main",
    "file" : "main.cpp",
    "message" : "Initialized Main Function",
    "time_elapsed" : 0.000627,
    "line" : 6,
    "level" : 1,
    "event_id" : 0
},
{
    "path" : "./logs/v2/20210913/36/full.json",
    "module_name" : "maps::init",
    "file" : "./maps/maps.h",
    "message" : "Initializing maps",
    "time_elapsed" : 0.142615,
    "line" : 32,
    "level" : 1,
    "event_id" : 2
},
{
    "path" : "./logs/v2/20210913/36/full.json",
    "module_name" : "maps::read_map_data",
    "file" : "./maps/maps.h",
    "message" : "Reading map data from ./maps/data/test.json",
    "time_elapsed" : 0.142895,
    "line" : 21,
    "level" : 1,
    "event_id" : 3
},
{
    "path" : "./logs/v2/20210913/36/full.json",
    "module_name" : "maps::read_map_data",
    "file" : "./maps/maps.h",
    "message" : "Reading map data from ./maps/data/test2.json",
    "time_elapsed" : 0.143655,
    "line" : 21,
    "level" : 1,
    "event_id" : 3
},
{
    "path" : "./logs/v2/20210913/36/full.json",
    "module_name" : "maps::read_map_data",
    "file" : "./maps/maps.h",
    "message" : "Reading map data from ./maps/data/test3.json",
    "time_elapsed" : 0.144323,
    "line" : 21,
    "level" : 1,
    "event_id" : 3
},
{
    "path" : "./logs/v2/20210913/36/full.json",
    "module_name" : "maps::init",
    "file" : "./maps/maps.h",
    "message" : "Maps initialized",
    "time_elapsed" : 0.144858,
    "line" : 38,
    "level" : 1,
    "event_id" : 2
},
{
    "path" : "./logs/v2/20210913/36/full.json",
    "module_name" : "shaders::init",
    "file" : "./shaders/shaders.h",
    "message" : "Initializing shaders",
    "time_elapsed" : 0.144966,
    "line" : 149,
    "level" : 1,
    "event_id" : 2
},
{
    "path" : "./logs/v2/20210913/36/full.json",
    "module_name" : "maps::read_shaders_data",
    "file" : "./shaders/shaders.h",
    "message" : "Reading shader data from ./shaders/data/light.json",
    "time_elapsed" : 0.145362,
    "line" : 137,
    "level" : 1,
    "event_id" : 3
},
{
    "path" : "./logs/v2/20210913/36/full.json",
    "module_name" : "maps::read_shaders_data",
    "file" : "./shaders/shaders.h",
    "message" : "Reading shader data from ./shaders/data/base.json",
    "time_elapsed" : 0.145575,
    "line" : 137,
    "level" : 1,
    "event_id" : 3
},
{
    "path" : "./logs/v2/20210913/36/full.json",
    "module_name" : "shaders::init",
    "file" : "./shaders/shaders.h",
    "message" : "Shaders initialized",
    "time_elapsed" : 0.164571,
    "line" : 162,
    "level" : 1,
    "event_id" : 2
},
{
    "path" : "./logs/v2/20210913/36/full.json",
    "module_name" : "textures::init",
    "file" : "./opengl/textures.h",
    "message" : "Initializing textures",
    "time_elapsed" : 0.164806,
    "line" : 134,
    "level" : 1,
    "event_id" : 2
},
{
    "path" : "./logs/v2/20210913/36/full.json",
    "module_name" : "textures::read_texture_data",
    "file" : "./opengl/textures.h",
    "message" : "Reading texture data from ./assets/data/barbarian.json",
    "time_elapsed" : 0.165128,
    "line" : 72,
    "level" : 1,
    "event_id" : 3
},
{
    "path" : "./logs/v2/20210913/36/full.json",
    "module_name" : "textures::read_texture_data",
    "file" : "./opengl/textures.h",
    "message" : "Reading texture data from ./assets/data/forest.json",
    "time_elapsed" : 0.16592,
    "line" : 72,
    "level" : 1,
    "event_id" : 3
},
{
    "path" : "./logs/v2/20210913/36/full.json",
    "module_name" : "textures::read_texture_data",
    "file" : "./opengl/textures.h",
    "message" : "Reading texture data from ./assets/data/items.json",
    "time_elapsed" : 0.166593,
    "line" : 72,
    "level" : 1,
    "event_id" : 3
},
{
    "path" : "./logs/v2/20210913/36/full.json",
    "module_name" : "textures::read_texture_data",
    "file" : "./opengl/textures.h",
    "message" : "Reading texture data from ./assets/data/stick.json",
    "time_elapsed" : 0.167023,
    "line" : 72,
    "level" : 1,
    "event_id" : 3
},
{
    "path" : "./logs/v2/20210913/36/full.json",
    "module_name" : "textures::read_texture_data",
    "file" : "./opengl/textures.h",
    "message" : "Reading texture data from ./assets/data/skeleton.json",
    "time_elapsed" : 0.167465,
    "line" : 72,
    "level" : 1,
    "event_id" : 3
},
{
    "path" : "./logs/v2/20210913/36/full.json",
    "module_name" : "textures::read_texture_data",
    "file" : "./opengl/textures.h",
    "message" : "Reading texture data from ./assets/data/dungeon.json",
    "time_elapsed" : 0.16789,
    "line" : 72,
    "level" : 1,
    "event_id" : 3
},
{
    "path" : "./logs/v2/20210913/36/full.json",
    "module_name" : "textures::load",
    "file" : "./opengl/textures.h",
    "message" : "Loading texture id:  1",
    "time_elapsed" : 0.168306,
    "line" : 91,
    "level" : 1,
    "event_id" : 4
},
{
    "path" : "./logs/v2/20210913/36/full.json",
    "module_name" : "textures::load_to_opengl",
    "file" : "./opengl/textures.h",
    "message" : "Loading texture id: 1 path: assets/dungeon.png to opengl",
    "time_elapsed" : 0.168508,
    "line" : 18,
    "level" : 1,
    "event_id" : 4
},
{
    "path" : "./logs/v2/20210913/36/full.json",
    "module_name" : "textures::load_to_opengl",
    "file" : "./opengl/textures.h",
    "message" : "Loaded texture new id: 1",
    "time_elapsed" : 0.169838,
    "line" : 62,
    "level" : 1,
    "event_id" : 4
},
{
    "path" : "./logs/v2/20210913/36/full.json",
    "module_name" : "textures::load",
    "file" : "./opengl/textures.h",
    "message" : "Loaded texture id:  1opengl texture id: 1",
    "time_elapsed" : 0.170015,
    "line" : 102,
    "level" : 1,
    "event_id" : 4
},
{
    "path" : "./logs/v2/20210913/36/full.json",
    "module_name" : "textures::load",
    "file" : "./opengl/textures.h",
    "message" : "Loading texture id:  2",
    "time_elapsed" : 0.170257,
    "line" : 91,
    "level" : 1,
    "event_id" : 4
},
{
    "path" : "./logs/v2/20210913/36/full.json",
    "module_name" : "textures::load_to_opengl",
    "file" : "./opengl/textures.h",
    "message" : "Loading texture id: 2 path: assets/forest.png to opengl",
    "time_elapsed" : 0.170371,
    "line" : 18,
    "level" : 1,
    "event_id" : 4
},
{
    "path" : "./logs/v2/20210913/36/full.json",
    "module_name" : "textures::load_to_opengl",
    "file" : "./opengl/textures.h",
    "message" : "Loaded texture new id: 2",
    "time_elapsed" : 0.174553,
    "line" : 62,
    "level" : 1,
    "event_id" : 4
},
{
    "path" : "./logs/v2/20210913/36/full.json",
    "module_name" : "textures::load",
    "file" : "./opengl/textures.h",
    "message" : "Loaded texture id:  2opengl texture id: 2",
    "time_elapsed" : 0.174736,
    "line" : 102,
    "level" : 1,
    "event_id" : 4
},
{
    "path" : "./logs/v2/20210913/36/full.json",
    "module_name" : "textures::load",
    "file" : "./opengl/textures.h",
    "message" : "Loading texture id:  3",
    "time_elapsed" : 0.17501,
    "line" : 91,
    "level" : 1,
    "event_id" : 4
},
{
    "path" : "./logs/v2/20210913/36/full.json",
    "module_name" : "textures::load_to_opengl",
    "file" : "./opengl/textures.h",
    "message" : "Loading texture id: 3 path: assets/barbarian.png to opengl",
    "time_elapsed" : 0.175231,
    "line" : 18,
    "level" : 1,
    "event_id" : 4
},
{
    "path" : "./logs/v2/20210913/36/full.json",
    "module_name" : "textures::load_to_opengl",
    "file" : "./opengl/textures.h",
    "message" : "Loaded texture new id: 3",
    "time_elapsed" : 0.177908,
    "line" : 62,
    "level" : 1,
    "event_id" : 4
},
{
    "path" : "./logs/v2/20210913/36/full.json",
    "module_name" : "textures::load",
    "file" : "./opengl/textures.h",
    "message" : "Loaded texture id:  3opengl texture id: 3",
    "time_elapsed" : 0.178066,
    "line" : 102,
    "level" : 1,
    "event_id" : 4
},
{
    "path" : "./logs/v2/20210913/36/full.json",
    "module_name" : "textures::load",
    "file" : "./opengl/textures.h",
    "message" : "Loading texture id:  4",
    "time_elapsed" : 0.17831,
    "line" : 91,
    "level" : 1,
    "event_id" : 4
},
{
    "path" : "./logs/v2/20210913/36/full.json",
    "module_name" : "textures::load_to_opengl",
    "file" : "./opengl/textures.h",
    "message" : "Loading texture id: 4 path: assets/stick.png to opengl",
    "time_elapsed" : 0.178425,
    "line" : 18,
    "level" : 1,
    "event_id" : 4
},
{
    "path" : "./logs/v2/20210913/36/full.json",
    "module_name" : "textures::load_to_opengl",
    "file" : "./opengl/textures.h",
    "message" : "Loaded texture new id: 4",
    "time_elapsed" : 0.180776,
    "line" : 62,
    "level" : 1,
    "event_id" : 4
},
{
    "path" : "./logs/v2/20210913/36/full.json",
    "module_name" : "textures::load",
    "file" : "./opengl/textures.h",
    "message" : "Loaded texture id:  4opengl texture id: 4",
    "time_elapsed" : 0.180968,
    "line" : 102,
    "level" : 1,
    "event_id" : 4
},
{
    "path" : "./logs/v2/20210913/36/full.json",
    "module_name" : "textures::load",
    "file" : "./opengl/textures.h",
    "message" : "Loading texture id:  5",
    "time_elapsed" : 0.181175,
    "line" : 91,
    "level" : 1,
    "event_id" : 4
},
{
    "path" : "./logs/v2/20210913/36/full.json",
    "module_name" : "textures::load_to_opengl",
    "file" : "./opengl/textures.h",
    "message" : "Loading texture id: 5 path: assets/items.png to opengl",
    "time_elapsed" : 0.181365,
    "line" : 18,
    "level" : 1,
    "event_id" : 4
},
{
    "path" : "./logs/v2/20210913/36/full.json",
    "module_name" : "textures::load_to_opengl",
    "file" : "./opengl/textures.h",
    "message" : "Loaded texture new id: 5",
    "time_elapsed" : 0.181719,
    "line" : 62,
    "level" : 1,
    "event_id" : 4
},
{
    "path" : "./logs/v2/20210913/36/full.json",
    "module_name" : "textures::load",
    "file" : "./opengl/textures.h",
    "message" : "Loaded texture id:  5opengl texture id: 5",
    "time_elapsed" : 0.18182,
    "line" : 102,
    "level" : 1,
    "event_id" : 4
},
{
    "path" : "./logs/v2/20210913/36/full.json",
    "module_name" : "textures::load",
    "file" : "./opengl/textures.h",
    "message" : "Loading texture id:  6",
    "time_elapsed" : 0.182036,
    "line" : 91,
    "level" : 1,
    "event_id" : 4
},
{
    "path" : "./logs/v2/20210913/36/full.json",
    "module_name" : "textures::load_to_opengl",
    "file" : "./opengl/textures.h",
    "message" : "Loading texture id: 6 path: assets/skeleton.png to opengl",
    "time_elapsed" : 0.182186,
    "line" : 18,
    "level" : 1,
    "event_id" : 4
},
{
    "path" : "./logs/v2/20210913/36/full.json",
    "module_name" : "textures::load_to_opengl",
    "file" : "./opengl/textures.h",
    "message" : "Loaded texture new id: 6",
    "time_elapsed" : 0.183691,
    "line" : 62,
    "level" : 1,
    "event_id" : 4
},
{
    "path" : "./logs/v2/20210913/36/full.json",
    "module_name" : "textures::load",
    "file" : "./opengl/textures.h",
    "message" : "Loaded texture id:  6opengl texture id: 6",
    "time_elapsed" : 0.183947,
    "line" : 102,
    "level" : 1,
    "event_id" : 4
},
{
    "path" : "./logs/v2/20210913/36/full.json",
    "module_name" : "textures::init",
    "file" : "./opengl/textures.h",
    "message" : "Textures initialized",
    "time_elapsed" : 0.184155,
    "line" : 147,
    "level" : 1,
    "event_id" : 2
},
{
    "path" : "./logs/v2/20210913/36/full.json",
    "module_name" : "menu::init",
    "file" : "./menu/menu.h",
    "message" : "Initializing menu",
    "time_elapsed" : 0.184315,
    "line" : 362,
    "level" : 1,
    "event_id" : 2
},
{
    "path" : "./logs/v2/20210913/36/full.json",
    "module_name" : "menu::read_button_data",
    "file" : "./menu/menu.h",
    "message" : "Reading button data from ./menu/data/main_new.json",
    "time_elapsed" : 0.184514,
    "line" : 352,
    "level" : 1,
    "event_id" : 3
},
{
    "path" : "./logs/v2/20210913/36/full.json",
    "module_name" : "menu::read_button_data",
    "file" : "./menu/menu.h",
    "message" : "Reading button data from ./menu/data/main_exit.json",
    "time_elapsed" : 0.184962,
    "line" : 352,
    "level" : 1,
    "event_id" : 3
},
{
    "path" : "./logs/v2/20210913/36/full.json",
    "module_name" : "menu::read_button_data",
    "file" : "./menu/menu.h",
    "message" : "Reading button data from ./menu/data/new_game_name.json",
    "time_elapsed" : 0.185526,
    "line" : 352,
    "level" : 1,
    "event_id" : 3
},
{
    "path" : "./logs/v2/20210913/36/full.json",
    "module_name" : "menu::read_button_data",
    "file" : "./menu/menu.h",
    "message" : "Reading button data from ./menu/data/main_settings.json",
    "time_elapsed" : 0.185984,
    "line" : 352,
    "level" : 1,
    "event_id" : 3
},
{
    "path" : "./logs/v2/20210913/36/full.json",
    "module_name" : "menu::read_button_data",
    "file" : "./menu/menu.h",
    "message" : "Reading button data from ./menu/data/back_to_main.json",
    "time_elapsed" : 0.186364,
    "line" : 352,
    "level" : 1,
    "event_id" : 3
},
{
    "path" : "./logs/v2/20210913/36/full.json",
    "module_name" : "menu::read_button_data",
    "file" : "./menu/menu.h",
    "message" : "Reading button data from ./menu/data/load_save.json",
    "time_elapsed" : 0.186685,
    "line" : 352,
    "level" : 1,
    "event_id" : 3
},
{
    "path" : "./logs/v2/20210913/36/full.json",
    "module_name" : "menu::read_button_data",
    "file" : "./menu/menu.h",
    "message" : "Reading button data from ./menu/data/main_load.json",
    "time_elapsed" : 0.18706,
    "line" : 352,
    "level" : 1,
    "event_id" : 3
},
{
    "path" : "./logs/v2/20210913/36/full.json",
    "module_name" : "menu::init",
    "file" : "./menu/menu.h",
    "message" : "Menu initialized",
    "time_elapsed" : 0.188093,
    "line" : 370,
    "level" : 1,
    "event_id" : 2
},
{
    "path" : "./logs/v2/20210913/36/full.json",
    "module_name" : "gui::init",
    "file" : "./gui/gui.h",
    "message" : "Initializing gui",
    "time_elapsed" : 0.188518,
    "line" : 39,
    "level" : 1,
    "event_id" : 2
},
{
    "path" : "./logs/v2/20210913/36/full.json",
    "module_name" : "gui::read_gui_data",
    "file" : "./gui/gui.h",
    "message" : "Reading GUI Window data from ./gui/data/debug.json",
    "time_elapsed" : 0.188708,
    "line" : 29,
    "level" : 1,
    "event_id" : 3
},
{
    "path" : "./logs/v2/20210913/36/full.json",
    "module_name" : "gui::init",
    "file" : "./gui/gui.h",
    "message" : "GUI initialized",
    "time_elapsed" : 0.189427,
    "line" : 46,
    "level" : 1,
    "event_id" : 2
},
{
    "path" : "./logs/v2/20210913/36/full.json",
    "module_name" : "menu::drop",
    "file" : "./menu/menu.h",
    "message" : "Dropping menu",
    "time_elapsed" : 1.454976,
    "line" : 376,
    "level" : 1,
    "event_id" : 5
},
{
    "path" : "./logs/v2/20210913/36/full.json",
    "module_name" : "gui::drop",
    "file" : "./gui/gui.h",
    "message" : "Dropping GUI",
    "time_elapsed" : 1.455696,
    "line" : 176,
    "level" : 1,
    "event_id" : 5
},
{
    "path" : "./logs/v2/20210913/36/full.json",
    "module_name" : "maps::drop_map",
    "file" : "./maps/maps.h",
    "message" : "Dropping  current map",
    "time_elapsed" : 1.456248,
    "line" : 246,
    "level" : 1,
    "event_id" : 5
},
{
    "path" : "./logs/v2/20210913/36/full.json",
    "module_name" : "menu::drop",
    "file" : "./menu/menu.h",
    "message" : "Dropping menu",
    "time_elapsed" : 1.573328,
    "line" : 376,
    "level" : 1,
    "event_id" : 5
},
{
    "path" : "./logs/v2/20210913/36/full.json",
    "module_name" : "gui::drop",
    "file" : "./gui/gui.h",
    "message" : "Dropping GUI",
    "time_elapsed" : 1.573874,
    "line" : 176,
    "level" : 1,
    "event_id" : 5
},
{
    "path" : "./logs/v2/20210913/36/full.json",
    "module_name" : "maps::drop_map",
    "file" : "./maps/maps.h",
    "message" : "Dropping  current map",
    "time_elapsed" : 1.574261,
    "line" : 246,
    "level" : 1,
    "event_id" : 5
},
{
    "path" : "./logs/v2/20210913/36/full.json",
    "module_name" : "menu::drop",
    "file" : "./menu/menu.h",
    "message" : "Dropping menu",
    "time_elapsed" : 1.679531,
    "line" : 376,
    "level" : 1,
    "event_id" : 5
},
{
    "path" : "./logs/v2/20210913/36/full.json",
    "module_name" : "gui::drop",
    "file" : "./gui/gui.h",
    "message" : "Dropping GUI",
    "time_elapsed" : 1.680055,
    "line" : 176,
    "level" : 1,
    "event_id" : 5
},
{
    "path" : "./logs/v2/20210913/36/full.json",
    "module_name" : "maps::drop_map",
    "file" : "./maps/maps.h",
    "message" : "Dropping  current map",
    "time_elapsed" : 1.680539,
    "line" : 246,
    "level" : 1,
    "event_id" : 5
},
{
    "path" : "./logs/v2/20210913/36/full.json",
    "module_name" : "menu::drop",
    "file" : "./menu/menu.h",
    "message" : "Dropping menu",
    "time_elapsed" : 1.701995,
    "line" : 376,
    "level" : 1,
    "event_id" : 5
},
{
    "path" : "./logs/v2/20210913/36/full.json",
    "module_name" : "gui::drop",
    "file" : "./gui/gui.h",
    "message" : "Dropping GUI",
    "time_elapsed" : 1.702449,
    "line" : 176,
    "level" : 1,
    "event_id" : 5
},
{
    "path" : "./logs/v2/20210913/36/full.json",
    "module_name" : "maps::drop_map",
    "file" : "./maps/maps.h",
    "message" : "Dropping  current map",
    "time_elapsed" : 1.702732,
    "line" : 246,
    "level" : 1,
    "event_id" : 5
},
{
    "path" : "./logs/v2/20210913/36/full.json",
    "module_name" : "menu::drop",
    "file" : "./menu/menu.h",
    "message" : "Dropping menu",
    "time_elapsed" : 1.83243,
    "line" : 376,
    "level" : 1,
    "event_id" : 5
},
{
    "path" : "./logs/v2/20210913/36/full.json",
    "module_name" : "gui::drop",
    "file" : "./gui/gui.h",
    "message" : "Dropping GUI",
    "time_elapsed" : 1.833151,
    "line" : 176,
    "level" : 1,
    "event_id" : 5
},
{
    "path" : "./logs/v2/20210913/36/full.json",
    "module_name" : "maps::drop_map",
    "file" : "./maps/maps.h",
    "message" : "Dropping  current map",
    "time_elapsed" : 1.833493,
    "line" : 246,
    "level" : 1,
    "event_id" : 5
},
{
    "path" : "./logs/v2/20210913/36/full.json",
    "module_name" : "menu::drop",
    "file" : "./menu/menu.h",
    "message" : "Dropping menu",
    "time_elapsed" : 1.968888,
    "line" : 376,
    "level" : 1,
    "event_id" : 5
},
{
    "path" : "./logs/v2/20210913/36/full.json",
    "module_name" : "gui::drop",
    "file" : "./gui/gui.h",
    "message" : "Dropping GUI",
    "time_elapsed" : 1.969442,
    "line" : 176,
    "level" : 1,
    "event_id" : 5
},
{
    "path" : "./logs/v2/20210913/36/full.json",
    "module_name" : "maps::drop_map",
    "file" : "./maps/maps.h",
    "message" : "Dropping  current map",
    "time_elapsed" : 1.969713,
    "line" : 246,
    "level" : 1,
    "event_id" : 5
},
{
    "path" : "./logs/v2/20210913/36/full.json",
    "module_name" : "maps::init_map",
    "file" : "./maps/maps.h",
    "message" : "Initializing level map id: 2 Map name: test3 Vertex width: 20 Vertex height: 16 Map texture id: 1",
    "time_elapsed" : 1.970142,
    "line" : 123,
    "level" : 1,
    "event_id" : 2
},
{
    "path" : "./logs/v2/20210913/36/full.json",
    "module_name" : "maps::load_map_from_file",
    "file" : "./maps/maps.h",
    "message" : "Loading map quads from maps/test3",
    "time_elapsed" : 1.970402,
    "line" : 51,
    "level" : 1,
    "event_id" : 4
},
{
    "path" : "./logs/v2/20210913/36/full.json",
    "module_name" : "maps::load_map_from_file",
    "file" : "./maps/maps.h",
    "message" : "Map quads loaded from maps/test3",
    "time_elapsed" : 1.972254,
    "line" : 109,
    "level" : 1,
    "event_id" : 4
},
{
    "path" : "./logs/v2/20210913/36/full.json",
    "module_name" : "maps::init_map",
    "file" : "./maps/maps.h",
    "message" : "Level map initialized",
    "time_elapsed" : 1.987759,
    "line" : 232,
    "level" : 1,
    "event_id" : 2
},
{
    "path" : "./logs/v2/20210913/36/full.json",
    "module_name" : "gui::drop",
    "file" : "./gui/gui.h",
    "message" : "Dropping GUI",
    "time_elapsed" : 2.028665,
    "line" : 176,
    "level" : 1,
    "event_id" : 5
},
{
    "path" : "./logs/v2/20210913/36/full.json",
    "module_name" : "gui::drop",
    "file" : "./gui/gui.h",
    "message" : "Dropping GUI",
    "time_elapsed" : 2.072401,
    "line" : 176,
    "level" : 1,
    "event_id" : 5
},
{
    "path" : "./logs/v2/20210913/36/full.json",
    "module_name" : "gui::drop",
    "file" : "./gui/gui.h",
    "message" : "Dropping GUI",
    "time_elapsed" : 2.117384,
    "line" : 176,
    "level" : 1,
    "event_id" : 5
},
{
    "path" : "./logs/v2/20210913/36/full.json",
    "module_name" : "gui::drop",
    "file" : "./gui/gui.h",
    "message" : "Dropping GUI",
    "time_elapsed" : 2.162825,
    "line" : 176,
    "level" : 1,
    "event_id" : 5
},
{
    "path" : "./logs/v2/20210913/36/full.json",
    "module_name" : "gui::drop",
    "file" : "./gui/gui.h",
    "message" : "Dropping GUI",
    "time_elapsed" : 2.207485,
    "line" : 176,
    "level" : 1,
    "event_id" : 5
},
{
    "path" : "./logs/v2/20210913/36/full.json",
    "module_name" : "gui::drop",
    "file" : "./gui/gui.h",
    "message" : "Dropping GUI",
    "time_elapsed" : 2.253029,
    "line" : 176,
    "level" : 1,
    "event_id" : 5
},
{
    "path" : "./logs/v2/20210913/36/full.json",
    "module_name" : "gui::drop",
    "file" : "./gui/gui.h",
    "message" : "Dropping GUI",
    "time_elapsed" : 2.299163,
    "line" : 176,
    "level" : 1,
    "event_id" : 5
},
{
    "path" : "./logs/v2/20210913/36/full.json",
    "module_name" : "gui::drop",
    "file" : "./gui/gui.h",
    "message" : "Dropping GUI",
    "time_elapsed" : 2.343675,
    "line" : 176,
    "level" : 1,
    "event_id" : 5
},
{
    "path" : "./logs/v2/20210913/36/full.json",
    "module_name" : "gui::drop",
    "file" : "./gui/gui.h",
    "message" : "Dropping GUI",
    "time_elapsed" : 2.391371,
    "line" : 176,
    "level" : 1,
    "event_id" : 5
},
{
    "path" : "./logs/v2/20210913/36/full.json",
    "module_name" : "gui::drop",
    "file" : "./gui/gui.h",
    "message" : "Dropping GUI",
    "time_elapsed" : 2.437213,
    "line" : 176,
    "level" : 1,
    "event_id" : 5
},
{
    "path" : "./logs/v2/20210913/36/full.json",
    "module_name" : "gui::drop",
    "file" : "./gui/gui.h",
    "message" : "Dropping GUI",
    "time_elapsed" : 2.48217,
    "line" : 176,
    "level" : 1,
    "event_id" : 5
},
{
    "path" : "./logs/v2/20210913/36/full.json",
    "module_name" : "gui::drop",
    "file" : "./gui/gui.h",
    "message" : "Dropping GUI",
    "time_elapsed" : 2.526523,
    "line" : 176,
    "level" : 1,
    "event_id" : 5
},
{
    "path" : "./logs/v2/20210913/36/full.json",
    "module_name" : "gui::drop",
    "file" : "./gui/gui.h",
    "message" : "Dropping GUI",
    "time_elapsed" : 2.571489,
    "line" : 176,
    "level" : 1,
    "event_id" : 5
},
{
    "path" : "./logs/v2/20210913/36/full.json",
    "module_name" : "gui::drop",
    "file" : "./gui/gui.h",
    "message" : "Dropping GUI",
    "time_elapsed" : 2.617246,
    "line" : 176,
    "level" : 1,
    "event_id" : 5
},
{
    "path" : "./logs/v2/20210913/36/full.json",
    "module_name" : "gui::drop",
    "file" : "./gui/gui.h",
    "message" : "Dropping GUI",
    "time_elapsed" : 2.661981,
    "line" : 176,
    "level" : 1,
    "event_id" : 5
},
{
    "path" : "./logs/v2/20210913/36/full.json",
    "module_name" : "gui::drop",
    "file" : "./gui/gui.h",
    "message" : "Dropping GUI",
    "time_elapsed" : 2.709959,
    "line" : 176,
    "level" : 1,
    "event_id" : 5
},
{
    "path" : "./logs/v2/20210913/36/full.json",
    "module_name" : "gui::drop",
    "file" : "./gui/gui.h",
    "message" : "Dropping GUI",
    "time_elapsed" : 2.753961,
    "line" : 176,
    "level" : 1,
    "event_id" : 5
},
{
    "path" : "./logs/v2/20210913/36/full.json",
    "module_name" : "gui::drop",
    "file" : "./gui/gui.h",
    "message" : "Dropping GUI",
    "time_elapsed" : 2.796741,
    "line" : 176,
    "level" : 1,
    "event_id" : 5
},
{
    "path" : "./logs/v2/20210913/36/full.json",
    "module_name" : "gui::drop",
    "file" : "./gui/gui.h",
    "message" : "Dropping GUI",
    "time_elapsed" : 2.838701,
    "line" : 176,
    "level" : 1,
    "event_id" : 5
},
{
    "path" : "./logs/v2/20210913/36/full.json",
    "module_name" : "gui::drop",
    "file" : "./gui/gui.h",
    "message" : "Dropping GUI",
    "time_elapsed" : 2.883543,
    "line" : 176,
    "level" : 1,
    "event_id" : 5
},
{
    "path" : "./logs/v2/20210913/36/full.json",
    "module_name" : "gui::drop",
    "file" : "./gui/gui.h",
    "message" : "Dropping GUI",
    "time_elapsed" : 2.927688,
    "line" : 176,
    "level" : 1,
    "event_id" : 5
},
{
    "path" : "./logs/v2/20210913/36/full.json",
    "module_name" : "gui::drop",
    "file" : "./gui/gui.h",
    "message" : "Dropping GUI",
    "time_elapsed" : 2.973213,
    "line" : 176,
    "level" : 1,
    "event_id" : 5
},
{
    "path" : "./logs/v2/20210913/36/full.json",
    "module_name" : "gui::drop",
    "file" : "./gui/gui.h",
    "message" : "Dropping GUI",
    "time_elapsed" : 3.019088,
    "line" : 176,
    "level" : 1,
    "event_id" : 5
},
{
    "path" : "./logs/v2/20210913/36/full.json",
    "module_name" : "gui::drop",
    "file" : "./gui/gui.h",
    "message" : "Dropping GUI",
    "time_elapsed" : 3.066163,
    "line" : 176,
    "level" : 1,
    "event_id" : 5
},
{
    "path" : "./logs/v2/20210913/36/full.json",
    "module_name" : "gui::drop",
    "file" : "./gui/gui.h",
    "message" : "Dropping GUI",
    "time_elapsed" : 3.113073,
    "line" : 176,
    "level" : 1,
    "event_id" : 5
},
{
    "path" : "./logs/v2/20210913/36/full.json",
    "module_name" : "gui::drop",
    "file" : "./gui/gui.h",
    "message" : "Dropping GUI",
    "time_elapsed" : 3.16423,
    "line" : 176,
    "level" : 1,
    "event_id" : 5
},
{
    "path" : "./logs/v2/20210913/36/full.json",
    "module_name" : "gui::drop",
    "file" : "./gui/gui.h",
    "message" : "Dropping GUI",
    "time_elapsed" : 3.205796,
    "line" : 176,
    "level" : 1,
    "event_id" : 5
},
{
    "path" : "./logs/v2/20210913/36/full.json",
    "module_name" : "gui::drop",
    "file" : "./gui/gui.h",
    "message" : "Dropping GUI",
    "time_elapsed" : 3.242468,
    "line" : 176,
    "level" : 1,
    "event_id" : 5
},
{
    "path" : "./logs/v2/20210913/36/full.json",
    "module_name" : "gui::drop",
    "file" : "./gui/gui.h",
    "message" : "Dropping GUI",
    "time_elapsed" : 3.27924,
    "line" : 176,
    "level" : 1,
    "event_id" : 5
},
{
    "path" : "./logs/v2/20210913/36/full.json",
    "module_name" : "gui::drop",
    "file" : "./gui/gui.h",
    "message" : "Dropping GUI",
    "time_elapsed" : 3.315725,
    "line" : 176,
    "level" : 1,
    "event_id" : 5
},
{
    "path" : "./logs/v2/20210913/36/full.json",
    "module_name" : "gui::drop",
    "file" : "./gui/gui.h",
    "message" : "Dropping GUI",
    "time_elapsed" : 3.351375,
    "line" : 176,
    "level" : 1,
    "event_id" : 5
},
{
    "path" : "./logs/v2/20210913/36/full.json",
    "module_name" : "gui::drop",
    "file" : "./gui/gui.h",
    "message" : "Dropping GUI",
    "time_elapsed" : 3.386924,
    "line" : 176,
    "level" : 1,
    "event_id" : 5
},
{
    "path" : "./logs/v2/20210913/36/full.json",
    "module_name" : "gui::drop",
    "file" : "./gui/gui.h",
    "message" : "Dropping GUI",
    "time_elapsed" : 3.425753,
    "line" : 176,
    "level" : 1,
    "event_id" : 5
},
{
    "path" : "./logs/v2/20210913/36/full.json",
    "module_name" : "gui::drop",
    "file" : "./gui/gui.h",
    "message" : "Dropping GUI",
    "time_elapsed" : 3.462159,
    "line" : 176,
    "level" : 1,
    "event_id" : 5
},
{
    "path" : "./logs/v2/20210913/36/full.json",
    "module_name" : "gui::drop",
    "file" : "./gui/gui.h",
    "message" : "Dropping GUI",
    "time_elapsed" : 3.499007,
    "line" : 176,
    "level" : 1,
    "event_id" : 5
},
{
    "path" : "./logs/v2/20210913/36/full.json",
    "module_name" : "gui::drop",
    "file" : "./gui/gui.h",
    "message" : "Dropping GUI",
    "time_elapsed" : 3.536871,
    "line" : 176,
    "level" : 1,
    "event_id" : 5
},
{
    "path" : "./logs/v2/20210913/36/full.json",
    "module_name" : "gui::drop",
    "file" : "./gui/gui.h",
    "message" : "Dropping GUI",
    "time_elapsed" : 3.573528,
    "line" : 176,
    "level" : 1,
    "event_id" : 5
},
{
    "path" : "./logs/v2/20210913/36/full.json",
    "module_name" : "gui::drop",
    "file" : "./gui/gui.h",
    "message" : "Dropping GUI",
    "time_elapsed" : 3.611112,
    "line" : 176,
    "level" : 1,
    "event_id" : 5
},
{
    "path" : "./logs/v2/20210913/36/full.json",
    "module_name" : "gui::drop",
    "file" : "./gui/gui.h",
    "message" : "Dropping GUI",
    "time_elapsed" : 3.648509,
    "line" : 176,
    "level" : 1,
    "event_id" : 5
},
{
    "path" : "./logs/v2/20210913/36/full.json",
    "module_name" : "gui::drop",
    "file" : "./gui/gui.h",
    "message" : "Dropping GUI",
    "time_elapsed" : 3.68527,
    "line" : 176,
    "level" : 1,
    "event_id" : 5
},
{
    "path" : "./logs/v2/20210913/36/full.json",
    "module_name" : "gui::drop",
    "file" : "./gui/gui.h",
    "message" : "Dropping GUI",
    "time_elapsed" : 3.722173,
    "line" : 176,
    "level" : 1,
    "event_id" : 5
},
{
    "path" : "./logs/v2/20210913/36/full.json",
    "module_name" : "gui::drop",
    "file" : "./gui/gui.h",
    "message" : "Dropping GUI",
    "time_elapsed" : 3.759301,
    "line" : 176,
    "level" : 1,
    "event_id" : 5
},
{
    "path" : "./logs/v2/20210913/36/full.json",
    "module_name" : "gui::drop",
    "file" : "./gui/gui.h",
    "message" : "Dropping GUI",
    "time_elapsed" : 3.795723,
    "line" : 176,
    "level" : 1,
    "event_id" : 5
},
{
    "path" : "./logs/v2/20210913/36/full.json",
    "module_name" : "gui::drop",
    "file" : "./gui/gui.h",
    "message" : "Dropping GUI",
    "time_elapsed" : 3.833586,
    "line" : 176,
    "level" : 1,
    "event_id" : 5
},
{
    "path" : "./logs/v2/20210913/36/full.json",
    "module_name" : "gui::drop",
    "file" : "./gui/gui.h",
    "message" : "Dropping GUI",
    "time_elapsed" : 3.875777,
    "line" : 176,
    "level" : 1,
    "event_id" : 5
},
{
    "path" : "./logs/v2/20210913/36/full.json",
    "module_name" : "gui::drop",
    "file" : "./gui/gui.h",
    "message" : "Dropping GUI",
    "time_elapsed" : 3.913038,
    "line" : 176,
    "level" : 1,
    "event_id" : 5
},
{
    "path" : "./logs/v2/20210913/36/full.json",
    "module_name" : "gui::drop",
    "file" : "./gui/gui.h",
    "message" : "Dropping GUI",
    "time_elapsed" : 3.949315,
    "line" : 176,
    "level" : 1,
    "event_id" : 5
},
{
    "path" : "./logs/v2/20210913/36/full.json",
    "module_name" : "gui::drop",
    "file" : "./gui/gui.h",
    "message" : "Dropping GUI",
    "time_elapsed" : 3.987812,
    "line" : 176,
    "level" : 1,
    "event_id" : 5
},
{
    "path" : "./logs/v2/20210913/36/full.json",
    "module_name" : "gui::drop",
    "file" : "./gui/gui.h",
    "message" : "Dropping GUI",
    "time_elapsed" : 4.025934,
    "line" : 176,
    "level" : 1,
    "event_id" : 5
},
{
    "path" : "./logs/v2/20210913/36/full.json",
    "module_name" : "gui::drop",
    "file" : "./gui/gui.h",
    "message" : "Dropping GUI",
    "time_elapsed" : 4.06274,
    "line" : 176,
    "level" : 1,
    "event_id" : 5
},
{
    "path" : "./logs/v2/20210913/36/full.json",
    "module_name" : "gui::drop",
    "file" : "./gui/gui.h",
    "message" : "Dropping GUI",
    "time_elapsed" : 4.09968,
    "line" : 176,
    "level" : 1,
    "event_id" : 5
},
{
    "path" : "./logs/v2/20210913/36/full.json",
    "module_name" : "gui::drop",
    "file" : "./gui/gui.h",
    "message" : "Dropping GUI",
    "time_elapsed" : 4.137521,
    "line" : 176,
    "level" : 1,
    "event_id" : 5
},
{
    "path" : "./logs/v2/20210913/36/full.json",
    "module_name" : "gui::drop",
    "file" : "./gui/gui.h",
    "message" : "Dropping GUI",
    "time_elapsed" : 4.174425,
    "line" : 176,
    "level" : 1,
    "event_id" : 5
},
{
    "path" : "./logs/v2/20210913/36/full.json",
    "module_name" : "gui::drop",
    "file" : "./gui/gui.h",
    "message" : "Dropping GUI",
    "time_elapsed" : 4.211954,
    "line" : 176,
    "level" : 1,
    "event_id" : 5
},
{
    "path" : "./logs/v2/20210913/36/full.json",
    "module_name" : "gui::drop",
    "file" : "./gui/gui.h",
    "message" : "Dropping GUI",
    "time_elapsed" : 4.248912,
    "line" : 176,
    "level" : 1,
    "event_id" : 5
},
{
    "path" : "./logs/v2/20210913/36/full.json",
    "module_name" : "gui::drop",
    "file" : "./gui/gui.h",
    "message" : "Dropping GUI",
    "time_elapsed" : 4.285366,
    "line" : 176,
    "level" : 1,
    "event_id" : 5
},
{
    "path" : "./logs/v2/20210913/36/full.json",
    "module_name" : "gui::drop",
    "file" : "./gui/gui.h",
    "message" : "Dropping GUI",
    "time_elapsed" : 4.321752,
    "line" : 176,
    "level" : 1,
    "event_id" : 5
},
{
    "path" : "./logs/v2/20210913/36/full.json",
    "module_name" : "gui::drop",
    "file" : "./gui/gui.h",
    "message" : "Dropping GUI",
    "time_elapsed" : 4.358451,
    "line" : 176,
    "level" : 1,
    "event_id" : 5
},
{
    "path" : "./logs/v2/20210913/36/full.json",
    "module_name" : "gui::drop",
    "file" : "./gui/gui.h",
    "message" : "Dropping GUI",
    "time_elapsed" : 4.396391,
    "line" : 176,
    "level" : 1,
    "event_id" : 5
},
{
    "path" : "./logs/v2/20210913/36/full.json",
    "module_name" : "gui::drop",
    "file" : "./gui/gui.h",
    "message" : "Dropping GUI",
    "time_elapsed" : 4.434509,
    "line" : 176,
    "level" : 1,
    "event_id" : 5
},
{
    "path" : "./logs/v2/20210913/36/full.json",
    "module_name" : "gui::drop",
    "file" : "./gui/gui.h",
    "message" : "Dropping GUI",
    "time_elapsed" : 4.471358,
    "line" : 176,
    "level" : 1,
    "event_id" : 5
},
{
    "path" : "./logs/v2/20210913/36/full.json",
    "module_name" : "gui::drop",
    "file" : "./gui/gui.h",
    "message" : "Dropping GUI",
    "time_elapsed" : 4.509201,
    "line" : 176,
    "level" : 1,
    "event_id" : 5
},
{
    "path" : "./logs/v2/20210913/36/full.json",
    "module_name" : "gui::drop",
    "file" : "./gui/gui.h",
    "message" : "Dropping GUI",
    "time_elapsed" : 4.548024,
    "line" : 176,
    "level" : 1,
    "event_id" : 5
},
{
    "path" : "./logs/v2/20210913/36/full.json",
    "module_name" : "gui::drop",
    "file" : "./gui/gui.h",
    "message" : "Dropping GUI",
    "time_elapsed" : 4.599891,
    "line" : 176,
    "level" : 1,
    "event_id" : 5
},
{
    "path" : "./logs/v2/20210913/36/full.json",
    "module_name" : "gui::drop",
    "file" : "./gui/gui.h",
    "message" : "Dropping GUI",
    "time_elapsed" : 4.653177,
    "line" : 176,
    "level" : 1,
    "event_id" : 5
},
{
    "path" : "./logs/v2/20210913/36/full.json",
    "module_name" : "gui::drop",
    "file" : "./gui/gui.h",
    "message" : "Dropping GUI",
    "time_elapsed" : 4.706663,
    "line" : 176,
    "level" : 1,
    "event_id" : 5
},
{
    "path" : "./logs/v2/20210913/36/full.json",
    "module_name" : "gui::drop",
    "file" : "./gui/gui.h",
    "message" : "Dropping GUI",
    "time_elapsed" : 4.761513,
    "line" : 176,
    "level" : 1,
    "event_id" : 5
},
{
    "path" : "./logs/v2/20210913/36/full.json",
    "module_name" : "gui::drop",
    "file" : "./gui/gui.h",
    "message" : "Dropping GUI",
    "time_elapsed" : 4.815827,
    "line" : 176,
    "level" : 1,
    "event_id" : 5
},
{
    "path" : "./logs/v2/20210913/36/full.json",
    "module_name" : "gui::drop",
    "file" : "./gui/gui.h",
    "message" : "Dropping GUI",
    "time_elapsed" : 4.867526,
    "line" : 176,
    "level" : 1,
    "event_id" : 5
},
{
    "path" : "./logs/v2/20210913/36/full.json",
    "module_name" : "gui::drop",
    "file" : "./gui/gui.h",
    "message" : "Dropping GUI",
    "time_elapsed" : 4.904358,
    "line" : 176,
    "level" : 1,
    "event_id" : 5
},
{
    "path" : "./logs/v2/20210913/36/full.json",
    "module_name" : "gui::drop",
    "file" : "./gui/gui.h",
    "message" : "Dropping GUI",
    "time_elapsed" : 4.941713,
    "line" : 176,
    "level" : 1,
    "event_id" : 5
},
{
    "path" : "./logs/v2/20210913/36/full.json",
    "module_name" : "gui::drop",
    "file" : "./gui/gui.h",
    "message" : "Dropping GUI",
    "time_elapsed" : 4.977931,
    "line" : 176,
    "level" : 1,
    "event_id" : 5
},
{
    "path" : "./logs/v2/20210913/36/full.json",
    "module_name" : "gui::drop",
    "file" : "./gui/gui.h",
    "message" : "Dropping GUI",
    "time_elapsed" : 5.019108,
    "line" : 176,
    "level" : 1,
    "event_id" : 5
},
{
    "path" : "./logs/v2/20210913/36/full.json",
    "module_name" : "gui::drop",
    "file" : "./gui/gui.h",
    "message" : "Dropping GUI",
    "time_elapsed" : 5.058958,
    "line" : 176,
    "level" : 1,
    "event_id" : 5
},
{
    "path" : "./logs/v2/20210913/36/full.json",
    "module_name" : "gui::drop",
    "file" : "./gui/gui.h",
    "message" : "Dropping GUI",
    "time_elapsed" : 5.096531,
    "line" : 176,
    "level" : 1,
    "event_id" : 5
},
{
    "path" : "./logs/v2/20210913/36/full.json",
    "module_name" : "gui::drop",
    "file" : "./gui/gui.h",
    "message" : "Dropping GUI",
    "time_elapsed" : 5.135226,
    "line" : 176,
    "level" : 1,
    "event_id" : 5
},
{
    "path" : "./logs/v2/20210913/36/full.json",
    "module_name" : "gui::drop",
    "file" : "./gui/gui.h",
    "message" : "Dropping GUI",
    "time_elapsed" : 5.174412,
    "line" : 176,
    "level" : 1,
    "event_id" : 5
},
{
    "path" : "./logs/v2/20210913/36/full.json",
    "module_name" : "gui::drop",
    "file" : "./gui/gui.h",
    "message" : "Dropping GUI",
    "time_elapsed" : 5.214694,
    "line" : 176,
    "level" : 1,
    "event_id" : 5
},
{
    "path" : "./logs/v2/20210913/36/full.json",
    "module_name" : "gui::drop",
    "file" : "./gui/gui.h",
    "message" : "Dropping GUI",
    "time_elapsed" : 5.251737,
    "line" : 176,
    "level" : 1,
    "event_id" : 5
},
{
    "path" : "./logs/v2/20210913/36/full.json",
    "module_name" : "gui::drop",
    "file" : "./gui/gui.h",
    "message" : "Dropping GUI",
    "time_elapsed" : 5.288726,
    "line" : 176,
    "level" : 1,
    "event_id" : 5
},
{
    "path" : "./logs/v2/20210913/36/full.json",
    "module_name" : "gui::drop",
    "file" : "./gui/gui.h",
    "message" : "Dropping GUI",
    "time_elapsed" : 5.324985,
    "line" : 176,
    "level" : 1,
    "event_id" : 5
},
{
    "path" : "./logs/v2/20210913/36/full.json",
    "module_name" : "gui::drop",
    "file" : "./gui/gui.h",
    "message" : "Dropping GUI",
    "time_elapsed" : 5.365706,
    "line" : 176,
    "level" : 1,
    "event_id" : 5
},
{
    "path" : "./logs/v2/20210913/36/full.json",
    "module_name" : "gui::drop",
    "file" : "./gui/gui.h",
    "message" : "Dropping GUI",
    "time_elapsed" : 5.407944,
    "line" : 176,
    "level" : 1,
    "event_id" : 5
},
{
    "path" : "./logs/v2/20210913/36/full.json",
    "module_name" : "gui::drop",
    "file" : "./gui/gui.h",
    "message" : "Dropping GUI",
    "time_elapsed" : 5.449292,
    "line" : 176,
    "level" : 1,
    "event_id" : 5
},
{
    "path" : "./logs/v2/20210913/36/full.json",
    "module_name" : "gui::drop",
    "file" : "./gui/gui.h",
    "message" : "Dropping GUI",
    "time_elapsed" : 5.486966,
    "line" : 176,
    "level" : 1,
    "event_id" : 5
},
{
    "path" : "./logs/v2/20210913/36/full.json",
    "module_name" : "gui::drop",
    "file" : "./gui/gui.h",
    "message" : "Dropping GUI",
    "time_elapsed" : 5.524616,
    "line" : 176,
    "level" : 1,
    "event_id" : 5
},
{
    "path" : "./logs/v2/20210913/36/full.json",
    "module_name" : "gui::drop",
    "file" : "./gui/gui.h",
    "message" : "Dropping GUI",
    "time_elapsed" : 5.56555,
    "line" : 176,
    "level" : 1,
    "event_id" : 5
},
{
    "path" : "./logs/v2/20210913/36/full.json",
    "module_name" : "gui::drop",
    "file" : "./gui/gui.h",
    "message" : "Dropping GUI",
    "time_elapsed" : 5.602654,
    "line" : 176,
    "level" : 1,
    "event_id" : 5
},
{
    "path" : "./logs/v2/20210913/36/full.json",
    "module_name" : "gui::drop",
    "file" : "./gui/gui.h",
    "message" : "Dropping GUI",
    "time_elapsed" : 5.640962,
    "line" : 176,
    "level" : 1,
    "event_id" : 5
},
{
    "path" : "./logs/v2/20210913/36/full.json",
    "module_name" : "gui::drop",
    "file" : "./gui/gui.h",
    "message" : "Dropping GUI",
    "time_elapsed" : 5.678133,
    "line" : 176,
    "level" : 1,
    "event_id" : 5
},
{
    "path" : "./logs/v2/20210913/36/full.json",
    "module_name" : "gui::drop",
    "file" : "./gui/gui.h",
    "message" : "Dropping GUI",
    "time_elapsed" : 5.715864,
    "line" : 176,
    "level" : 1,
    "event_id" : 5
},
{
    "path" : "./logs/v2/20210913/36/full.json",
    "module_name" : "gui::drop",
    "file" : "./gui/gui.h",
    "message" : "Dropping GUI",
    "time_elapsed" : 5.753997,
    "line" : 176,
    "level" : 1,
    "event_id" : 5
},
{
    "path" : "./logs/v2/20210913/36/full.json",
    "module_name" : "gui::drop",
    "file" : "./gui/gui.h",
    "message" : "Dropping GUI",
    "time_elapsed" : 5.792925,
    "line" : 176,
    "level" : 1,
    "event_id" : 5
},
{
    "path" : "./logs/v2/20210913/36/full.json",
    "module_name" : "gui::drop",
    "file" : "./gui/gui.h",
    "message" : "Dropping GUI",
    "time_elapsed" : 5.830386,
    "line" : 176,
    "level" : 1,
    "event_id" : 5
},
{
    "path" : "./logs/v2/20210913/36/full.json",
    "module_name" : "gui::drop",
    "file" : "./gui/gui.h",
    "message" : "Dropping GUI",
    "time_elapsed" : 5.868258,
    "line" : 176,
    "level" : 1,
    "event_id" : 5
},
{
    "path" : "./logs/v2/20210913/36/full.json",
    "module_name" : "gui::drop",
    "file" : "./gui/gui.h",
    "message" : "Dropping GUI",
    "time_elapsed" : 5.90546,
    "line" : 176,
    "level" : 1,
    "event_id" : 5
},
{
    "path" : "./logs/v2/20210913/36/full.json",
    "module_name" : "gui::drop",
    "file" : "./gui/gui.h",
    "message" : "Dropping GUI",
    "time_elapsed" : 5.944945,
    "line" : 176,
    "level" : 1,
    "event_id" : 5
},
{
    "path" : "./logs/v2/20210913/36/full.json",
    "module_name" : "gui::drop",
    "file" : "./gui/gui.h",
    "message" : "Dropping GUI",
    "time_elapsed" : 5.984458,
    "line" : 176,
    "level" : 1,
    "event_id" : 5
},
{
    "path" : "./logs/v2/20210913/36/full.json",
    "module_name" : "gui::drop",
    "file" : "./gui/gui.h",
    "message" : "Dropping GUI",
    "time_elapsed" : 6.023858,
    "line" : 176,
    "level" : 1,
    "event_id" : 5
},
{
    "path" : "./logs/v2/20210913/36/full.json",
    "module_name" : "gui::drop",
    "file" : "./gui/gui.h",
    "message" : "Dropping GUI",
    "time_elapsed" : 6.064186,
    "line" : 176,
    "level" : 1,
    "event_id" : 5
},
{
    "path" : "./logs/v2/20210913/36/full.json",
    "module_name" : "gui::drop",
    "file" : "./gui/gui.h",
    "message" : "Dropping GUI",
    "time_elapsed" : 6.115765,
    "line" : 176,
    "level" : 1,
    "event_id" : 5
},
{
    "path" : "./logs/v2/20210913/36/full.json",
    "module_name" : "gui::drop",
    "file" : "./gui/gui.h",
    "message" : "Dropping GUI",
    "time_elapsed" : 6.167289,
    "line" : 176,
    "level" : 1,
    "event_id" : 5
},
{
    "path" : "./logs/v2/20210913/36/full.json",
    "module_name" : "gui::drop",
    "file" : "./gui/gui.h",
    "message" : "Dropping GUI",
    "time_elapsed" : 6.208785,
    "line" : 176,
    "level" : 1,
    "event_id" : 5
},
{
    "path" : "./logs/v2/20210913/36/full.json",
    "module_name" : "gui::drop",
    "file" : "./gui/gui.h",
    "message" : "Dropping GUI",
    "time_elapsed" : 6.246966,
    "line" : 176,
    "level" : 1,
    "event_id" : 5
},
{
    "path" : "./logs/v2/20210913/36/full.json",
    "module_name" : "gui::drop",
    "file" : "./gui/gui.h",
    "message" : "Dropping GUI",
    "time_elapsed" : 6.286279,
    "line" : 176,
    "level" : 1,
    "event_id" : 5
},
{
    "path" : "./logs/v2/20210913/36/full.json",
    "module_name" : "gui::drop",
    "file" : "./gui/gui.h",
    "message" : "Dropping GUI",
    "time_elapsed" : 6.326058,
    "line" : 176,
    "level" : 1,
    "event_id" : 5
},
{
    "path" : "./logs/v2/20210913/36/full.json",
    "module_name" : "gui::drop",
    "file" : "./gui/gui.h",
    "message" : "Dropping GUI",
    "time_elapsed" : 6.365701,
    "line" : 176,
    "level" : 1,
    "event_id" : 5
},
{
    "path" : "./logs/v2/20210913/36/full.json",
    "module_name" : "gui::drop",
    "file" : "./gui/gui.h",
    "message" : "Dropping GUI",
    "time_elapsed" : 6.40365,
    "line" : 176,
    "level" : 1,
    "event_id" : 5
},
{
    "path" : "./logs/v2/20210913/36/full.json",
    "module_name" : "gui::drop",
    "file" : "./gui/gui.h",
    "message" : "Dropping GUI",
    "time_elapsed" : 6.443457,
    "line" : 176,
    "level" : 1,
    "event_id" : 5
},
{
    "path" : "./logs/v2/20210913/36/full.json",
    "module_name" : "gui::drop",
    "file" : "./gui/gui.h",
    "message" : "Dropping GUI",
    "time_elapsed" : 6.483254,
    "line" : 176,
    "level" : 1,
    "event_id" : 5
},
{
    "path" : "./logs/v2/20210913/36/full.json",
    "module_name" : "gui::drop",
    "file" : "./gui/gui.h",
    "message" : "Dropping GUI",
    "time_elapsed" : 6.522289,
    "line" : 176,
    "level" : 1,
    "event_id" : 5
},
{
    "path" : "./logs/v2/20210913/36/full.json",
    "module_name" : "gui::drop",
    "file" : "./gui/gui.h",
    "message" : "Dropping GUI",
    "time_elapsed" : 6.564295,
    "line" : 176,
    "level" : 1,
    "event_id" : 5
},
{
    "path" : "./logs/v2/20210913/36/full.json",
    "module_name" : "gui::drop",
    "file" : "./gui/gui.h",
    "message" : "Dropping GUI",
    "time_elapsed" : 6.605192,
    "line" : 176,
    "level" : 1,
    "event_id" : 5
},
{
    "path" : "./logs/v2/20210913/36/full.json",
    "module_name" : "gui::drop",
    "file" : "./gui/gui.h",
    "message" : "Dropping GUI",
    "time_elapsed" : 6.646338,
    "line" : 176,
    "level" : 1,
    "event_id" : 5
},
{
    "path" : "./logs/v2/20210913/36/full.json",
    "module_name" : "gui::drop",
    "file" : "./gui/gui.h",
    "message" : "Dropping GUI",
    "time_elapsed" : 6.688616,
    "line" : 176,
    "level" : 1,
    "event_id" : 5
},
{
    "path" : "./logs/v2/20210913/36/full.json",
    "module_name" : "gui::drop",
    "file" : "./gui/gui.h",
    "message" : "Dropping GUI",
    "time_elapsed" : 6.728653,
    "line" : 176,
    "level" : 1,
    "event_id" : 5
},
{
    "path" : "./logs/v2/20210913/36/full.json",
    "module_name" : "gui::drop",
    "file" : "./gui/gui.h",
    "message" : "Dropping GUI",
    "time_elapsed" : 6.769996,
    "line" : 176,
    "level" : 1,
    "event_id" : 5
},
{
    "path" : "./logs/v2/20210913/36/full.json",
    "module_name" : "gui::drop",
    "file" : "./gui/gui.h",
    "message" : "Dropping GUI",
    "time_elapsed" : 6.812454,
    "line" : 176,
    "level" : 1,
    "event_id" : 5
},
{
    "path" : "./logs/v2/20210913/36/full.json",
    "module_name" : "gui::drop",
    "file" : "./gui/gui.h",
    "message" : "Dropping GUI",
    "time_elapsed" : 6.936972,
    "line" : 176,
    "level" : 1,
    "event_id" : 5
},
{
    "path" : "./logs/v2/20210913/36/full.json",
    "module_name" : "textures::drop",
    "file" : "./opengl/textures.h",
    "message" : "Dropping textures",
    "time_elapsed" : 6.97489,
    "line" : 157,
    "level" : 1,
    "event_id" : 5
},
{
    "path" : "./logs/v2/20210913/36/full.json",
    "module_name" : "shaders::drop",
    "file" : "./shaders/shaders.h",
    "message" : "Dropping current shader",
    "time_elapsed" : 6.975635,
    "line" : 169,
    "level" : 1,
    "event_id" : 5
},
{
    "path" : "./logs/v2/20210913/36/full.json",
    "module_name" : "maps::drop_map",
    "file" : "./maps/maps.h",
    "message" : "Dropping  current map",
    "time_elapsed" : 6.975784,
    "line" : 246,
    "level" : 1,
    "event_id" : 5
},
{
    "path" : "./logs/v2/20210913/36/full.json",
    "module_name" : "main::main",
    "file" : "main.cpp",
    "message" : "Game Exit",
    "time_elapsed" : 6.998478,
    "line" : 61,
    "level" : 1,
    "event_id" : 1
}]
